tsmoothie/__init__.py
tsmoothie/bootstrap.py
tsmoothie/regression_basis.py
tsmoothie/smoother.py
tsmoothie/utils_class.py
tsmoothie/utils_func.py
tsmoothie-1.0.5.dist-info/LICENSE
tsmoothie-1.0.5.dist-info/METADATA
tsmoothie-1.0.5.dist-info/WHEEL
tsmoothie-1.0.5.dist-info/top_level.txt
tsmoothie-1.0.5.dist-info/RECORD
