Metadata-Version: 2.1
Name: tsmoothie
Version: 1.0.5
Summary: A python library for timeseries smoothing and outlier detection in a vectorized way.
Home-page: https://github.com/cerlymarco/tsmoothie
Author: Marco Cerliani
Author-email: cerlymarco@gmail.com
License: MIT
Requires-Python: >=3
License-File: LICENSE
Requires-Dist: numpy
Requires-Dist: scipy
Requires-Dist: simdkalman
